{
  "title": "For the Lawyers",
  "author": "Crossword Bot",
  "date": "2022-02-22",
  "height": 15,
  "width": 15,
  "grid": [
    [
      "N",
      "A",
      "D",
      "A",
      "#",
      "E",
      "T",
      "H",
      "E",
      "R",
      "#",
      "T",
      "E",
      "L",
      "S"
    ],
    [
      "A",
      "T",
      "O",
      "P",
      "#",
      "S",
      "O",
      "R",
      "B",
      "O",
      "#",
      "E",
      "D",
      "I",
      "T"
    ],
    [
      "A",
      "S",
      "G",
      "E",
      "N",
      "T",
      "L",
      "E",
      "A",
      "S",
      "A",
      "L",
      "A",
      "M",
      "B"
    ],
    [
      "C",
      "E",
      "T",
      "#",
      "O",
      "E",
      "D",
      "#",
      "Y",
      "I",
      "E",
      "L",
      "D",
      "E",
      "D"
    ],
    [
      "P",
      "A",
      "R",
      "A",
      "D",
      "E",
      "#",
      "O",
      "W",
      "E",
      "N",
      "S",
      "#",
      "#",
      "#"
    ],
    [
      "#",
      "#",
      "A",
      "B",
      "E",
      "#",
      "E",
      "P",
      "I",
      "#",
      "E",
      "O",
      "S",
      "I",
      "N"
    ],
    [
      "A",
      "R",
      "I",
      "A",
      "#",
      "R",
      "A",
      "I",
      "N",
      "D",
      "A",
      "N",
      "C",
      "E",
      "S"
    ],
    [
      "S",
      "A",
      "N",
      "#",
      "A",
      "B",
      "R",
      "A",
      "D",
      "E",
      "S",
      "#",
      "H",
      "S",
      "E"
    ],
    [
      "O",
      "V",
      "E",
      "R",
      "T",
      "H",
      "E",
      "T",
      "O",
      "P",
      "#",
      "R",
      "O",
      "T",
      "C"
    ],
    [
      "N",
      "E",
      "R",
      "O",
      "S",
      "#",
      "D",
      "E",
      "W",
      "#",
      "T",
      "O",
      "O",
      "#",
      "#"
    ],
    [
      "#",
      "#",
      "#",
      "S",
      "T",
      "O",
      "S",
      "S",
      "#",
      "S",
      "E",
      "L",
      "L",
      "E",
      "R"
    ],
    [
      "S",
      "T",
      "A",
      "T",
      "U",
      "R",
      "E",
      "#",
      "A",
      "E",
      "S",
      "#",
      "R",
      "R",
      "R"
    ],
    [
      "C",
      "O",
      "M",
      "E",
      "D",
      "I",
      "A",
      "N",
      "B",
      "U",
      "T",
      "T",
      "O",
      "N",
      "S"
    ],
    [
      "A",
      "F",
      "A",
      "R",
      "#",
      "E",
      "L",
      "S",
      "E",
      "S",
      "#",
      "C",
      "O",
      "I",
      "T"
    ],
    [
      "R",
      "U",
      "T",
      "S",
      "#",
      "L",
      "S",
      "A",
      "T",
      "S",
      "#",
      "U",
      "M",
      "E",
      "A"
    ]
  ],
  "entries": [
    {
      "name": "A01",
      "word": "NADA",
      "clue": "Zilch",
      "cells": [
        [
          0,
          0
        ],
        [
          0,
          1
        ],
        [
          0,
          2
        ],
        [
          0,
          3
        ]
      ]
    },
    {
      "name": "A05",
      "word": "ETHER",
      "clue": "Old anesthetic",
      "cells": [
        [
          0,
          5
        ],
        [
          0,
          6
        ],
        [
          0,
          7
        ],
        [
          0,
          8
        ],
        [
          0,
          9
        ]
      ]
    },
    {
      "name": "A10",
      "word": "TELS",
      "clue": "Rolodex nos",
      "cells": [
        [
          0,
          11
        ],
        [
          0,
          12
        ],
        [
          0,
          13
        ],
        [
          0,
          14
        ]
      ]
    },
    {
      "name": "A14",
      "word": "ATOP",
      "clue": "On",
      "cells": [
        [
          1,
          0
        ],
        [
          1,
          1
        ],
        [
          1,
          2
        ],
        [
          1,
          3
        ]
      ]
    },
    {
      "name": "A15",
      "word": "SORBO",
      "clue": "Hercules portrayer Kevin",
      "cells": [
        [
          1,
          5
        ],
        [
          1,
          6
        ],
        [
          1,
          7
        ],
        [
          1,
          8
        ],
        [
          1,
          9
        ]
      ]
    },
    {
      "name": "A16",
      "word": "EDIT",
      "clue": "Revise",
      "cells": [
        [
          1,
          11
        ],
        [
          1,
          12
        ],
        [
          1,
          13
        ],
        [
          1,
          14
        ]
      ]
    },
    {
      "name": "A17",
      "word": "ASGENTLEASALAMB",
      "clue": "Totally harmless",
      "cells": [
        [
          2,
          0
        ],
        [
          2,
          1
        ],
        [
          2,
          2
        ],
        [
          2,
          3
        ],
        [
          2,
          4
        ],
        [
          2,
          5
        ],
        [
          2,
          6
        ],
        [
          2,
          7
        ],
        [
          2,
          8
        ],
        [
          2,
          9
        ],
        [
          2,
          10
        ],
        [
          2,
          11
        ],
        [
          2,
          12
        ],
        [
          2,
          13
        ],
        [
          2,
          14
        ]
      ]
    },
    {
      "name": "A20",
      "word": "CET",
      "clue": "That: Fr",
      "cells": [
        [
          3,
          0
        ],
        [
          3,
          1
        ],
        [
          3,
          2
        ]
      ]
    },
    {
      "name": "A21",
      "word": "OED",
      "clue": "Brit. lexicon",
      "cells": [
        [
          3,
          4
        ],
        [
          3,
          5
        ],
        [
          3,
          6
        ]
      ]
    },
    {
      "name": "A22",
      "word": "YIELDED",
      "clue": "Gave way",
      "cells": [
        [
          3,
          8
        ],
        [
          3,
          9
        ],
        [
          3,
          10
        ],
        [
          3,
          11
        ],
        [
          3,
          12
        ],
        [
          3,
          13
        ],
        [
          3,
          14
        ]
      ]
    },
    {
      "name": "A23",
      "word": "PARADE",
      "clue": "Show off",
      "cells": [
        [
          4,
          0
        ],
        [
          4,
          1
        ],
        [
          4,
          2
        ],
        [
          4,
          3
        ],
        [
          4,
          4
        ],
        [
          4,
          5
        ]
      ]
    },
    {
      "name": "A25",
      "word": "OWENS",
      "clue": "Jesse of the 1936 Olympics",
      "cells": [
        [
          4,
          7
        ],
        [
          4,
          8
        ],
        [
          4,
          9
        ],
        [
          4,
          10
        ],
        [
          4,
          11
        ]
      ]
    },
    {
      "name": "A26",
      "word": "ABE",
      "clue": "Presidential nickname",
      "cells": [
        [
          5,
          2
        ],
        [
          5,
          3
        ],
        [
          5,
          4
        ]
      ]
    },
    {
      "name": "A27",
      "word": "EPI",
      "clue": "Prefix with center",
      "cells": [
        [
          5,
          6
        ],
        [
          5,
          7
        ],
        [
          5,
          8
        ]
      ]
    },
    {
      "name": "A28",
      "word": "EOSIN",
      "clue": "Red dye",
      "cells": [
        [
          5,
          10
        ],
        [
          5,
          11
        ],
        [
          5,
          12
        ],
        [
          5,
          13
        ],
        [
          5,
          14
        ]
      ]
    },
    {
      "name": "A32",
      "word": "ARIA",
      "clue": "Opera solo",
      "cells": [
        [
          6,
          0
        ],
        [
          6,
          1
        ],
        [
          6,
          2
        ],
        [
          6,
          3
        ]
      ]
    },
    {
      "name": "A34",
      "word": "RAINDANCES",
      "clue": "Some drought rituals",
      "cells": [
        [
          6,
          5
        ],
        [
          6,
          6
        ],
        [
          6,
          7
        ],
        [
          6,
          8
        ],
        [
          6,
          9
        ],
        [
          6,
          10
        ],
        [
          6,
          11
        ],
        [
          6,
          12
        ],
        [
          6,
          13
        ],
        [
          6,
          14
        ]
      ]
    },
    {
      "name": "A36",
      "word": "SAN",
      "clue": "Japanese honorific",
      "cells": [
        [
          7,
          0
        ],
        [
          7,
          1
        ],
        [
          7,
          2
        ]
      ]
    },
    {
      "name": "A37",
      "word": "ABRADES",
      "clue": "Wears away",
      "cells": [
        [
          7,
          4
        ],
        [
          7,
          5
        ],
        [
          7,
          6
        ],
        [
          7,
          7
        ],
        [
          7,
          8
        ],
        [
          7,
          9
        ],
        [
          7,
          10
        ]
      ]
    },
    {
      "name": "A38",
      "word": "HSE",
      "clue": "Residence: Abbr",
      "cells": [
        [
          7,
          12
        ],
        [
          7,
          13
        ],
        [
          7,
          14
        ]
      ]
    },
    {
      "name": "A39",
      "word": "OVERTHETOP",
      "clue": "Excessive",
      "cells": [
        [
          8,
          0
        ],
        [
          8,
          1
        ],
        [
          8,
          2
        ],
        [
          8,
          3
        ],
        [
          8,
          4
        ],
        [
          8,
          5
        ],
        [
          8,
          6
        ],
        [
          8,
          7
        ],
        [
          8,
          8
        ],
        [
          8,
          9
        ]
      ]
    },
    {
      "name": "A41",
      "word": "ROTC",
      "clue": "Campus military org",
      "cells": [
        [
          8,
          11
        ],
        [
          8,
          12
        ],
        [
          8,
          13
        ],
        [
          8,
          14
        ]
      ]
    },
    {
      "name": "A42",
      "word": "NEROS",
      "clue": "Peter and Franco",
      "cells": [
        [
          9,
          0
        ],
        [
          9,
          1
        ],
        [
          9,
          2
        ],
        [
          9,
          3
        ],
        [
          9,
          4
        ]
      ]
    },
    {
      "name": "A43",
      "word": "DEW",
      "clue": "Morning moisture",
      "cells": [
        [
          9,
          6
        ],
        [
          9,
          7
        ],
        [
          9,
          8
        ]
      ]
    },
    {
      "name": "A44",
      "word": "TOO",
      "clue": "Overly",
      "cells": [
        [
          9,
          10
        ],
        [
          9,
          11
        ],
        [
          9,
          12
        ]
      ]
    },
    {
      "name": "A45",
      "word": "STOSS",
      "clue": "Facing a glacier",
      "cells": [
        [
          10,
          3
        ],
        [
          10,
          4
        ],
        [
          10,
          5
        ],
        [
          10,
          6
        ],
        [
          10,
          7
        ]
      ]
    },
    {
      "name": "A47",
      "word": "SELLER",
      "clue": "Merchant",
      "cells": [
        [
          10,
          9
        ],
        [
          10,
          10
        ],
        [
          10,
          11
        ],
        [
          10,
          12
        ],
        [
          10,
          13
        ],
        [
          10,
          14
        ]
      ]
    },
    {
      "name": "A50",
      "word": "STATURE",
      "clue": "Height",
      "cells": [
        [
          11,
          0
        ],
        [
          11,
          1
        ],
        [
          11,
          2
        ],
        [
          11,
          3
        ],
        [
          11,
          4
        ],
        [
          11,
          5
        ],
        [
          11,
          6
        ]
      ]
    },
    {
      "name": "A53",
      "word": "AES",
      "clue": "Loser to D.D.E",
      "cells": [
        [
          11,
          8
        ],
        [
          11,
          9
        ],
        [
          11,
          10
        ]
      ]
    },
    {
      "name": "A54",
      "word": "RRR",
      "clue": "Basic education trio",
      "cells": [
        [
          11,
          12
        ],
        [
          11,
          13
        ],
        [
          11,
          14
        ]
      ]
    },
    {
      "name": "A55",
      "word": "COMEDIANBUTTONS",
      "clue": "Occupation and surname of Aaron Schwatt",
      "cells": [
        [
          12,
          0
        ],
        [
          12,
          1
        ],
        [
          12,
          2
        ],
        [
          12,
          3
        ],
        [
          12,
          4
        ],
        [
          12,
          5
        ],
        [
          12,
          6
        ],
        [
          12,
          7
        ],
        [
          12,
          8
        ],
        [
          12,
          9
        ],
        [
          12,
          10
        ],
        [
          12,
          11
        ],
        [
          12,
          12
        ],
        [
          12,
          13
        ],
        [
          12,
          14
        ]
      ]
    },
    {
      "name": "A58",
      "word": "AFAR",
      "clue": "At a distance",
      "cells": [
        [
          13,
          0
        ],
        [
          13,
          1
        ],
        [
          13,
          2
        ],
        [
          13,
          3
        ]
      ]
    },
    {
      "name": "A59",
      "word": "ELSES",
      "clue": "It's nobody ____ business",
      "cells": [
        [
          13,
          5
        ],
        [
          13,
          6
        ],
        [
          13,
          7
        ],
        [
          13,
          8
        ],
        [
          13,
          9
        ]
      ]
    },
    {
      "name": "A60",
      "word": "COIT",
      "clue": "San Francisco's ____ Tower",
      "cells": [
        [
          13,
          11
        ],
        [
          13,
          12
        ],
        [
          13,
          13
        ],
        [
          13,
          14
        ]
      ]
    },
    {
      "name": "A61",
      "word": "RUTS",
      "clue": "Furrows",
      "cells": [
        [
          14,
          0
        ],
        [
          14,
          1
        ],
        [
          14,
          2
        ],
        [
          14,
          3
        ]
      ]
    },
    {
      "name": "A62",
      "word": "LSATS",
      "clue": "Exams for future attorneys",
      "cells": [
        [
          14,
          5
        ],
        [
          14,
          6
        ],
        [
          14,
          7
        ],
        [
          14,
          8
        ],
        [
          14,
          9
        ]
      ]
    },
    {
      "name": "A63",
      "word": "UMEA",
      "clue": "Swedish university town",
      "cells": [
        [
          14,
          11
        ],
        [
          14,
          12
        ],
        [
          14,
          13
        ],
        [
          14,
          14
        ]
      ]
    },
    {
      "name": "D01",
      "word": "NAACP",
      "clue": "Civil rights org",
      "cells": [
        [
          0,
          0
        ],
        [
          1,
          0
        ],
        [
          2,
          0
        ],
        [
          3,
          0
        ],
        [
          4,
          0
        ]
      ]
    },
    {
      "name": "D02",
      "word": "ATSEA",
      "clue": "Bewildered",
      "cells": [
        [
          0,
          1
        ],
        [
          1,
          1
        ],
        [
          2,
          1
        ],
        [
          3,
          1
        ],
        [
          4,
          1
        ]
      ]
    },
    {
      "name": "D03",
      "word": "DOGTRAINER",
      "clue": "Whistle-blower at obedience school",
      "cells": [
        [
          0,
          2
        ],
        [
          1,
          2
        ],
        [
          2,
          2
        ],
        [
          3,
          2
        ],
        [
          4,
          2
        ],
        [
          5,
          2
        ],
        [
          6,
          2
        ],
        [
          7,
          2
        ],
        [
          8,
          2
        ],
        [
          9,
          2
        ]
      ]
    },
    {
      "name": "D04",
      "word": "APE",
      "clue": "Mimic",
      "cells": [
        [
          0,
          3
        ],
        [
          1,
          3
        ],
        [
          2,
          3
        ]
      ]
    },
    {
      "name": "D05",
      "word": "ESTEE",
      "clue": "First name in cosmetics",
      "cells": [
        [
          0,
          5
        ],
        [
          1,
          5
        ],
        [
          2,
          5
        ],
        [
          3,
          5
        ],
        [
          4,
          5
        ]
      ]
    },
    {
      "name": "D06",
      "word": "TOLD",
      "clue": "Related",
      "cells": [
        [
          0,
          6
        ],
        [
          1,
          6
        ],
        [
          2,
          6
        ],
        [
          3,
          6
        ]
      ]
    },
    {
      "name": "D07",
      "word": "HRE",
      "clue": "Charlemagne's realm: Abbr",
      "cells": [
        [
          0,
          7
        ],
        [
          1,
          7
        ],
        [
          2,
          7
        ]
      ]
    },
    {
      "name": "D08",
      "word": "EBAYWINDOW",
      "clue": "What might have the heading \"Collectibles\" or \"Toys & Hobbies\"?",
      "cells": [
        [
          0,
          8
        ],
        [
          1,
          8
        ],
        [
          2,
          8
        ],
        [
          3,
          8
        ],
        [
          4,
          8
        ],
        [
          5,
          8
        ],
        [
          6,
          8
        ],
        [
          7,
          8
        ],
        [
          8,
          8
        ],
        [
          9,
          8
        ]
      ]
    },
    {
      "name": "D09",
      "word": "ROSIE",
      "clue": "WWII riveter",
      "cells": [
        [
          0,
          9
        ],
        [
          1,
          9
        ],
        [
          2,
          9
        ],
        [
          3,
          9
        ],
        [
          4,
          9
        ]
      ]
    },
    {
      "name": "D10",
      "word": "TELLSON",
      "clue": "Rats out",
      "cells": [
        [
          0,
          11
        ],
        [
          1,
          11
        ],
        [
          2,
          11
        ],
        [
          3,
          11
        ],
        [
          4,
          11
        ],
        [
          5,
          11
        ],
        [
          6,
          11
        ]
      ]
    },
    {
      "name": "D11",
      "word": "EDAD",
      "clue": "Age, in Acapulco",
      "cells": [
        [
          0,
          12
        ],
        [
          1,
          12
        ],
        [
          2,
          12
        ],
        [
          3,
          12
        ]
      ]
    },
    {
      "name": "D12",
      "word": "LIME",
      "clue": "Citrus fruit",
      "cells": [
        [
          0,
          13
        ],
        [
          1,
          13
        ],
        [
          2,
          13
        ],
        [
          3,
          13
        ]
      ]
    },
    {
      "name": "D13",
      "word": "STBD",
      "clue": "Naut. right",
      "cells": [
        [
          0,
          14
        ],
        [
          1,
          14
        ],
        [
          2,
          14
        ],
        [
          3,
          14
        ]
      ]
    },
    {
      "name": "D18",
      "word": "NODE",
      "clue": "Protuberance",
      "cells": [
        [
          2,
          4
        ],
        [
          3,
          4
        ],
        [
          4,
          4
        ],
        [
          5,
          4
        ]
      ]
    },
    {
      "name": "D19",
      "word": "AENEAS",
      "clue": "Trojan hero",
      "cells": [
        [
          2,
          10
        ],
        [
          3,
          10
        ],
        [
          4,
          10
        ],
        [
          5,
          10
        ],
        [
          6,
          10
        ],
        [
          7,
          10
        ]
      ]
    },
    {
      "name": "D24",
      "word": "ABA",
      "clue": "Lawyers' org",
      "cells": [
        [
          4,
          3
        ],
        [
          5,
          3
        ],
        [
          6,
          3
        ]
      ]
    },
    {
      "name": "D25",
      "word": "OPIATES",
      "clue": "Narcotics",
      "cells": [
        [
          4,
          7
        ],
        [
          5,
          7
        ],
        [
          6,
          7
        ],
        [
          7,
          7
        ],
        [
          8,
          7
        ],
        [
          9,
          7
        ],
        [
          10,
          7
        ]
      ]
    },
    {
      "name": "D27",
      "word": "EAREDSEALS",
      "clue": "Barrel-shaped marine mammals",
      "cells": [
        [
          5,
          6
        ],
        [
          6,
          6
        ],
        [
          7,
          6
        ],
        [
          8,
          6
        ],
        [
          9,
          6
        ],
        [
          10,
          6
        ],
        [
          11,
          6
        ],
        [
          12,
          6
        ],
        [
          13,
          6
        ],
        [
          14,
          6
        ]
      ]
    },
    {
      "name": "D29",
      "word": "SCHOOLROOM",
      "clue": "Learning place",
      "cells": [
        [
          5,
          12
        ],
        [
          6,
          12
        ],
        [
          7,
          12
        ],
        [
          8,
          12
        ],
        [
          9,
          12
        ],
        [
          10,
          12
        ],
        [
          11,
          12
        ],
        [
          12,
          12
        ],
        [
          13,
          12
        ],
        [
          14,
          12
        ]
      ]
    },
    {
      "name": "D30",
      "word": "IEST",
      "clue": "Superlative suffix",
      "cells": [
        [
          5,
          13
        ],
        [
          6,
          13
        ],
        [
          7,
          13
        ],
        [
          8,
          13
        ]
      ]
    },
    {
      "name": "D31",
      "word": "NSEC",
      "clue": "Tiny fraction of a min",
      "cells": [
        [
          5,
          14
        ],
        [
          6,
          14
        ],
        [
          7,
          14
        ],
        [
          8,
          14
        ]
      ]
    },
    {
      "name": "D32",
      "word": "ASON",
      "clue": "Unto us ____ is given",
      "cells": [
        [
          6,
          0
        ],
        [
          7,
          0
        ],
        [
          8,
          0
        ],
        [
          9,
          0
        ]
      ]
    },
    {
      "name": "D33",
      "word": "RAVE",
      "clue": "Four-star review",
      "cells": [
        [
          6,
          1
        ],
        [
          7,
          1
        ],
        [
          8,
          1
        ],
        [
          9,
          1
        ]
      ]
    },
    {
      "name": "D34",
      "word": "RBH",
      "clue": "President after U.S.G",
      "cells": [
        [
          6,
          5
        ],
        [
          7,
          5
        ],
        [
          8,
          5
        ]
      ]
    },
    {
      "name": "D35",
      "word": "DEP",
      "clue": "Sheriff's asst",
      "cells": [
        [
          6,
          9
        ],
        [
          7,
          9
        ],
        [
          8,
          9
        ]
      ]
    },
    {
      "name": "D37",
      "word": "ATSTUD",
      "clue": "Like some retired racehorses",
      "cells": [
        [
          7,
          4
        ],
        [
          8,
          4
        ],
        [
          9,
          4
        ],
        [
          10,
          4
        ],
        [
          11,
          4
        ],
        [
          12,
          4
        ]
      ]
    },
    {
      "name": "D40",
      "word": "ROSTERS",
      "clue": "Lists",
      "cells": [
        [
          8,
          3
        ],
        [
          9,
          3
        ],
        [
          10,
          3
        ],
        [
          11,
          3
        ],
        [
          12,
          3
        ],
        [
          13,
          3
        ],
        [
          14,
          3
        ]
      ]
    },
    {
      "name": "D41",
      "word": "ROL",
      "clue": "Spin, in some product names",
      "cells": [
        [
          8,
          11
        ],
        [
          9,
          11
        ],
        [
          10,
          11
        ]
      ]
    },
    {
      "name": "D44",
      "word": "TEST",
      "clue": "Exam",
      "cells": [
        [
          9,
          10
        ],
        [
          10,
          10
        ],
        [
          11,
          10
        ],
        [
          12,
          10
        ]
      ]
    },
    {
      "name": "D46",
      "word": "ORIEL",
      "clue": "Bay window",
      "cells": [
        [
          10,
          5
        ],
        [
          11,
          5
        ],
        [
          12,
          5
        ],
        [
          13,
          5
        ],
        [
          14,
          5
        ]
      ]
    },
    {
      "name": "D47",
      "word": "SEUSS",
      "clue": "Grinch creator",
      "cells": [
        [
          10,
          9
        ],
        [
          11,
          9
        ],
        [
          12,
          9
        ],
        [
          13,
          9
        ],
        [
          14,
          9
        ]
      ]
    },
    {
      "name": "D48",
      "word": "ERNIE",
      "clue": "Bert's buddy",
      "cells": [
        [
          10,
          13
        ],
        [
          11,
          13
        ],
        [
          12,
          13
        ],
        [
          13,
          13
        ],
        [
          14,
          13
        ]
      ]
    },
    {
      "name": "D49",
      "word": "RRSTA",
      "clue": "Train stop: Abbr",
      "cells": [
        [
          10,
          14
        ],
        [
          11,
          14
        ],
        [
          12,
          14
        ],
        [
          13,
          14
        ],
        [
          14,
          14
        ]
      ]
    },
    {
      "name": "D50",
      "word": "SCAR",
      "clue": "Cicatrix",
      "cells": [
        [
          11,
          0
        ],
        [
          12,
          0
        ],
        [
          13,
          0
        ],
        [
          14,
          0
        ]
      ]
    },
    {
      "name": "D51",
      "word": "TOFU",
      "clue": "Bean curd",
      "cells": [
        [
          11,
          1
        ],
        [
          12,
          1
        ],
        [
          13,
          1
        ],
        [
          14,
          1
        ]
      ]
    },
    {
      "name": "D52",
      "word": "AMAT",
      "clue": "Amo, amas, ____",
      "cells": [
        [
          11,
          2
        ],
        [
          12,
          2
        ],
        [
          13,
          2
        ],
        [
          14,
          2
        ]
      ]
    },
    {
      "name": "D53",
      "word": "ABET",
      "clue": "Encourage",
      "cells": [
        [
          11,
          8
        ],
        [
          12,
          8
        ],
        [
          13,
          8
        ],
        [
          14,
          8
        ]
      ]
    },
    {
      "name": "D56",
      "word": "NSA",
      "clue": "Code-cracking org",
      "cells": [
        [
          12,
          7
        ],
        [
          13,
          7
        ],
        [
          14,
          7
        ]
      ]
    },
    {
      "name": "D57",
      "word": "TCU",
      "clue": "Fort Worth sch",
      "cells": [
        [
          12,
          11
        ],
        [
          13,
          11
        ],
        [
          14,
          11
        ]
      ]
    }
  ]
}